[
  {
    "stt": 5,
    "thitruong": "TT khác",
    "mathanhpham": "RS*R50D10PQ",
    "some": 2,
    "soluong": 2720,
    "maukhuanbandau": 0,
    "mauedotoxin": 10,
    "mauchietxuat": 0,
    "mautinhnang": 13,
    "maueog": 0,
    "maukhac": 0,
    "Tray": "Tray S",
    "tongmau": 23,
    "tongsanxuat": 2743,
    "slpalet": 3.14,
    "maxpalet/me": 7,
    "quennong": "5D",
    "Batch_ID": "trays7175",
    "Batch_Total": 6.25,
    "Batch_ID_encoded": 172
  },
  {
    "stt": 86,
    "thitruong": "TT khác",
    "mathanhpham": "RS*R40G10PQ",
    "some": 1,
    "soluong": 2700,
    "maukhuanbandau": 0,
    "mauedotoxin": 10,
    "mauchietxuat": 0,
    "mautinhnang": 13,
    "maueog": 0,
    "maukhac": 0,
    "Tray": "Tray S",
    "tongmau": 23,
    "tongsanxuat": 2723,
    "slpalet": 3.11,
    "maxpalet/me": 7,
    "quennong": "4G",
    "Batch_ID": "trays7175",
    "Batch_Total": 6.25,
    "Batch_ID_encoded": 172
  }
]